Workbook

Sheet Assumptions
A1: Category | B1: Metric | C1: Value | D1: Notes
A2: Coach Acquisition | B2: Founder's Circle (Initial) | C2: 20 | D2: Your GTM target for Nov/Dec 2024.
A3: Coach Acquisition | B3: New Signups (Months 1-3) | C3: 15 | D3: Per month. Driven by initial launch marketing.
A4: Coach Acquisition | B4: New Signups (Months 4-6) | C4: 20 | D4: Per month. Content marketing & SEO begin to contribute.
A5: Coach Acquisition | B5: New Signups (Months 7-12) | C5: 30 | D5: Per month. Word of mouth and early paid ads.
A6: Coach Acquisition | B6: New Signups (Year 2) | C6: 40 | D6: Per month. Established brand presence.
A7: Coach Acquisition | B7: Coach Activation Rate | C7: 0.6 | D7: Percentage of new signups who publish a service and connect Stripe.
A8: Coach Acquisition | B8: Monthly Coach Churn Rate | C8: 0.03 | D8: Natural churn of inactive or unsuccessful coaches.
A9: Activity per Coach | B9: Scheduled Sessions/Mo (Months 1-3) | C9: 1.5 | D9: Per active coach. Primarily their existing clients.
A10: Activity per Coach | B10: Scheduled Sessions/Mo (Months 4-12) | C10: 3
A11: Activity per Coach | B11: Scheduled Sessions/Mo (Year 2) | C11: 4
A12: Activity per Coach | B12: Live Session Mins/Mo (Months 1-3) | C12: 20 | D12: Per active coach. Early adoption of the feature.
A13: Activity per Coach | B13: Live Session Mins/Mo (Months 4-12) | C13: 45
A14: Activity per Coach | B14: Live Session Mins/Mo (Year 2) | C14: 60
A15: Activity per Coach | B15: Programs Sold/Mo (Months 1-3) | C15: 2 | D15: Per active coach. Low price point makes it an easy initial sale.
A16: Activity per Coach | B16: Programs Sold/Mo (Months 4-12) | C16: 5
A17: Activity per Coach | B17: Programs Sold/Mo (Year 2) | C17: 8
A18: Financials | B18: Avg. Scheduled Session Price | C18: 100 | D18: In CHF.
A19: Financials | B19: Avg. Live Session Price per Minute | C19: 2 | D19: In CHF.
A20: Financials | B20: Avg. Program Price | C20: 30 | D20: In CHF.
A21: Financials | B21: Platform Take Rate | C21: 0.099 | D21: Your commission on GMV.
A22: Financials | B22: Stripe Variable Fee | C22: 0.029 | D22: Standard assumption for Stripe processing.
A23: Financials | B23: Stripe Fixed Fee | C23: 0.3 | D23: In CHF, per transaction.

Sheet Monatsmodell
A1: Metric | B1: Month 1 | C1: Month 2
A2: Month Number | B2: 1 | C2: =B2+1 -> 2
A3: Coach Funnel
A4: Opening Active Coaches | B4: =Assumptions!C2 -> 20 | C4: =B8 -> 28
A5: New Coach Signups | B5: =Assumptions!C3 -> 15 | C5: =IF(C2<=3,Assumptions!C3,IF(C2<=6,Assumptions!C4,IF(C2<=12,Assumptions!C5,Assumptions!C6))) -> 15
A6: New Activated Coaches | B6: =ROUND(B5*Assumptions!C7,0) -> 9 | C6: =ROUND(C5*Assumptions!C7,0) -> 9
A7: Churned Coaches | B7: =ROUND(B4*Assumptions!C8,0) -> 1 | C7: =ROUND(C4*Assumptions!C8,0) -> 1
A8: Closing Active Coaches | B8: =B4+B6-B7 -> 28 | C8: =C4+C6-C7 -> 36
A9: Gross Merchandise Volume (GMV)
A10: Sessions/Mo/Coach (Assumption) | B10: =Assumptions!C9 -> 1.5 | C10: =IF(C2<=3,Assumptions!C9,IF(C2<=12,Assumptions!C10,Assumptions!C11)) -> 1.5
A11: Total Scheduled Sessions | B11: =B8*B10 -> 42 | C11: =C8*C10 -> 54
A12: GMV from Scheduled Sessions | B12: =B11*Assumptions!C18 -> 4200 | C12: =C11*Assumptions!C18 -> 5400
A13: Live Mins/Mo/Coach (Assumption) | B13: =Assumptions!C12 -> 20 | C13: =IF(C2<=3,Assumptions!C12,IF(C2<=12,Assumptions!C13,Assumptions!C14)) -> 20
A14: Total Live Session Minutes | B14: =B8*B13 -> 560 | C14: =C8*C13 -> 720
A15: GMV from Live Sessions | B15: =B14*Assumptions!C19 -> 1120 | C15: =C14*Assumptions!C19 -> 1440
A16: Programs Sold/Mo/Coach (Assumption) | B16: =Assumptions!C15 -> 2 | C16: =IF(C2<=3,Assumptions!C15,IF(C2<=12,Assumptions!C16,Assumptions!C17)) -> 2
A17: Total Programs Sold | B17: =B8*B16 -> 56 | C17: =C8*B16 -> 72
A18: GMV from Programs | B18: =B17*Assumptions!C20 -> 1680 | C18: =C17*Assumptions!C20 -> 2160
A19: Total GMV | B19: =B12+B15+B18 -> 7000 | C19: =C12+C15+C18 -> 9000
A20: Revenue & Costs
A21: Gross Platform Revenue | B21: =B19*Assumptions!C21 -> 693 | C21: =C19*Assumptions!C21 -> 891
A22: Total Transactions | B22: =B11+ROUNDUP(B14/30,0)+B17 -> 117 | C22: =C11+ROUNDUP(C14/30,0)+C17 -> 150
A23: Stripe Variable Cost | B23: =B19*Assumptions!C22 -> 203 | C23: =C19*Assumptions!C22 -> 261
A24: Stripe Fixed Cost | B24: =B22*Assumptions!C23 -> 35.1 | C24: =C22*Assumptions!C23 -> 45
A25: Total Payment Processing Cost | B25: =B23+B24 -> 238.1 | C25: =C23+C24 -> 306
A26: Net Platform Revenue | B26: =B21-B25 -> 454.9 | C26: =C21-C25 -> 585

Sheet Jahresmodell
A1: Metric | B1: Year 1 Projection (Formulas) | C1: Year 2 Projection (Formulas)
A2: Ending Active Coaches | B2: =Monatsmodell!M8 -> 0 | C2: =Monatsmodell!Y8 -> 0
A3: Total GMV | B3: =SUM(Monatsmodell!B19:M19) -> 16000 | C3: =SUM(Monatsmodell!N19:Y19) -> 0
A4: GMV from Sessions | B4: =SUM(Monatsmodell!B12:M12) -> 9600 | C4: =SUM(Monatsmodell!N12:Y12) -> 0
A5: GMV from Live Sessions | B5: =SUM(Monatsmodell!B15:M15) -> 2560 | C5: =SUM(Monatsmodell!N15:Y15) -> 0
A6: GMV from Programs | B6: =SUM(Monatsmodell!B18:M18) -> 3840 | C6: =SUM(Monatsmodell!N18:Y18) -> 0
A7: Gross Platform Revenue | B7: =SUM(Monatsmodell!B21:M21) -> 1584 | C7: =SUM(Monatsmodell!N21:Y21) -> 0
A8: Payment Processing Costs | B8: =SUM(Monatsmodell!B25:M25) -> 544.1 | C8: =SUM(Monatsmodell!N25:Y25) -> 0
A9: Net Platform Revenue | B9: =SUM(Monatsmodell!B26:M26) -> 1039.9 | C9: =SUM(Monatsmodell!N26:Y26) -> 0
A10: Avg. Monthly Net Revenue | B10: =B9/12 -> 86.658333 | C10: =C9/12 -> 0
A11: Avg. Revenue per Active Coach (ARPU) | B11: =B9/B2 -> #DIV/0! | C11: =C9/C2 -> #DIV/0!
